shrub/__init__.py
shrub/base.py
shrub/command.py
shrub/config.py
shrub/operations.py
shrub/py.typed
shrub/task.py
shrub/v2/__init__.py
shrub/v2/command.py
shrub/v2/dict_creation_util.py
shrub/v2/project.py
shrub/v2/task.py
shrub/v2/variant.py
shrub/v3/__init__.py
shrub/v3/evg_build_variant.py
shrub/v3/evg_command.py
shrub/v3/evg_project.py
shrub/v3/evg_task.py
shrub/v3/evg_task_group.py
shrub/v3/shrub_service.py
shrub/variant.py
shrub_py-3.10.0.dist-info/LICENSE
shrub_py-3.10.0.dist-info/METADATA
shrub_py-3.10.0.dist-info/WHEEL
shrub_py-3.10.0.dist-info/RECORD
