Metadata-Version: 2.3
Name: shrub.py
Version: 3.10.0
Summary: Library for creating evergreen configurations
License: Apache-2.0
Author: DevProd Services & Integrations Team
Author-email: devprod-si-team@mongodb.com
Requires-Python: >=3.8.1
Classifier: License :: OSI Approved :: Apache Software License
Classifier: Programming Language :: Python :: 3
Classifier: Programming Language :: Python :: 3.9
Classifier: Programming Language :: Python :: 3.10
Classifier: Programming Language :: Python :: 3.11
Classifier: Programming Language :: Python :: 3.12
Classifier: Programming Language :: Python :: 3.13
Requires-Dist: PyYaml (>=5.1,<7.0)
Requires-Dist: croniter (>=1.4.1,<2.0.0)
Requires-Dist: dataclasses (>=0.7,<0.8) ; python_version == "3.6"
Requires-Dist: pydantic (>=2.0,<3.0)
Requires-Dist: typing-extensions (>=4,<5)
Project-URL: Repository, https://github.com/evergreen-ci/shrub.py
